net_scan/__init__.py
net_scan/__main__.py
Network_Scanner-1.0.2.dist-info/LICENSE
Network_Scanner-1.0.2.dist-info/METADATA
Network_Scanner-1.0.2.dist-info/WHEEL
Network_Scanner-1.0.2.dist-info/entry_points.txt
Network_Scanner-1.0.2.dist-info/top_level.txt
Network_Scanner-1.0.2.dist-info/RECORD
