Metadata-Version: 2.1
Name: Network-Scanner
Version: 1.0.2
Summary: Python-based tool which helps to scan the network
Home-page: https://github.com/adityakesarwani/Network-Scanner
Author: Aditya Kesarwani
Author-email: adkesarw@gmail.com
License: MIT
Platform: UNKNOWN
Classifier: License :: OSI Approved :: MIT License
Classifier: Programming Language :: Python :: 3.6
Classifier: Programming Language :: Python :: 3.7
Classifier: Programming Language :: Python :: 3.8
Classifier: Programming Language :: Python :: 3.9
License-File: LICENSE
Requires-Dist: aiodns
Requires-Dist: aioping
Requires-Dist: async-timeout
Requires-Dist: asyncio
Requires-Dist: cffi
Requires-Dist: ipaddress
Requires-Dist: mypy
Requires-Dist: mypy-extensions
Requires-Dist: pycares
Requires-Dist: pycparser
Requires-Dist: toml
Requires-Dist: typing
Requires-Dist: typing-extensions
